strictflow/__init__.py
strictflow/api.py
strictflow/core.py
strictflow-0.1.0.dist-info/METADATA
strictflow-0.1.0.dist-info/WHEEL
strictflow-0.1.0.dist-info/top_level.txt
strictflow-0.1.0.dist-info/RECORD
