Metadata-Version: 2.4
Name: strictflow
Version: 0.1.0
Summary: A lightweight, strict flow controller for enforcing thread-safe Read (P2) and Write (P1) priority in concurrent Python applications.
Author-email: chiro <chiro6466@gmail.com>
License-Expression: MIT
Project-URL: Homepage, https://github.com/chiro6466/strictflow/blob/main/strictflow
Keywords: concurrency,thread-safe,priority,locking,queue,strict
Classifier: Programming Language :: Python :: 3
Classifier: Programming Language :: Python :: 3.8
Classifier: Programming Language :: Python :: 3.9
Classifier: Programming Language :: Python :: 3.10
Classifier: Programming Language :: Python :: 3.11
Classifier: Programming Language :: Python :: 3.12
Classifier: Operating System :: OS Independent
Classifier: Development Status :: 4 - Beta
Classifier: Intended Audience :: Developers
Requires-Python: >=3.8
